{
  "source_file": "sample_document.txt",
  "chunk_index": 0,
  "total_chunks": 1,
  "token_count": 913,
  "page_number": 1,
  "timestamp": "2026-04-18T06:47:25",
  "context": {
    "previous_chapter": "",
    "next_chapter": "Możemy wyróżnić trzy główne rodzaje AI:",
    "previous_subchapter": "",
    "next_subchapter": "Możemy wyróżnić trzy główne rodzaje AI:",
    "previous_subsubchapter": "",
    "next_subsubchapter": "",
    "title": "Rozdział 1: Wstęp do sztucznej inteligencji",
    "subtitle": ""
  },
  "content": "Rozdział 1: Wstęp do sztucznej inteligencji\n\nSztuczna inteligencja (AI) to dziedzina informatyki zajmująca się tworzeniem systemów zdolnych do wykonywania zadań wymagających ludzkiej inteligencji. Do takich zadań należą między innymi uczenie się, rozumowanie, percepcja i rozwiązywanie problemów. 1. 1 Historia rozwoju AI\n\nHistoria sztucznej inteligencji rozpoczęła się w latach 50. XX wieku. Pierwsze koncepcje zostały przedstawione przez Alana Turinga, który zaproponował test mający na celu ocenę zdolności maszyny do myślenia. W 1956 roku odbyła się konferencja w Dartmouth, gdzie po raz pierwszy użyto terminu \"sztuczna inteligencja\". Było to przełomowe wydarzenie, które zapoczątkowało rozwój tej dziedziny. 1. 2 Rodzaje sztucznej inteligencji\n\nMożemy wyróżnić trzy główne rodzaje AI:\n\n- Słaba AI (Narrow AI): Systemy zaprojektowane do wykonywania konkretnych zadań, takie jak asystenci głosowi czy systemy rekomendacyjne. - Silna AI (General AI): Hipotetyczne systemy posiadające ludzki poziom inteligencji w różnych dziedzinach. - Superinteligencja: Teoretyczna forma AI przewyższająca ludzkie możliwości we wszystkich aspektach. Rozdział 2: Uczenie maszynowe\n\nUczenie maszynowe (Machine Learning) to poddziedzina sztucznej inteligencji koncentrująca się na opracowywaniu algorytmów, które mogą uczyć się na podstawie danych. 2. 1 Uczenie nadzorowane\n\nW uczeniu nadzorowanym model jest trenowany na danych zawierających zarówno wejścia, jak i oczekiwane wyjścia. Przykładami są klasyfikacja i regresja. 2. 2 Uczenie nienadzorowane\n\nW tym przypadku model pracuje z danymi nieoznaczonymi, odkrywając ukryte wzorce i struktury. Typowe zastosowania to klastrowanie i redukcja wymiarowości. 2. 3 Uczenie ze wzmocnieniem\n\nUczenie ze wzmocnieniem polega na trenowaniu agenta poprzez system nagród i kar. Agent uczy się optymalnej strategii działania w danym środowisku. Rozdział 3: Sieci neuronowe\n\nSieci neuronowe są inspirowane budową ludzkiego mózgu. Składają się z warstw połączonych neuronów, które przetwarzają informacje. 3. 1 Architektura sieci neuronowych\n\nPodstawowa sieć neuronowa składa się z trzech rodzajów warstw:\n- Warstwa wejściowa: Przyjmuje dane do przetworzenia\n- Warstwy ukryte: Przetwarzają informacje pośrednie\n- Warstwa wyjściowa: Generuje końcowy wynik\n\n3. 2 Głębokie uczenie\n\nGłębokie uczenie (Deep Learning) wykorzystuje wielowarstwowe sieci neuronowe do rozwiązywania złożonych problemów. Znajduje zastosowanie w rozpoznawaniu obrazów, przetwarzaniu języka naturalnego i wielu innych dziedzinach. Podsumowanie\n\nSztuczna inteligencja rozwija się dynamicznie, otwierając nowe możliwości w różnych dziedzinach życia. Od medycyny po transport, AI zmienia sposób, w jaki żyjemy i pracujemy. \n "
}
